README.md
setup.py
plyto/__init__.py
plyto/check_data.py
plyto/keras_accuracy_loss_callback.py
plyto/plyto.py
plyto/pytorch_loss_callback.py
plyto.egg-info/PKG-INFO
plyto.egg-info/SOURCES.txt
plyto.egg-info/dependency_links.txt
plyto.egg-info/requires.txt
plyto.egg-info/top_level.txt