Metadata-Version: 2.1
Name: plyto
Version: 0.1.0
Summary: Python Visualization Toolkit for Machine Learning and Data Exploration
Home-page: UNKNOWN
Author: Noah Stapp, Jenna Landy, and Alena Mueller
License: UNKNOWN
Platform: UNKNOWN
